odoo/addons/auth_saml/LICENSE
odoo/addons/auth_saml/README.rst
odoo/addons/auth_saml/__init__.py
odoo/addons/auth_saml/__manifest__.py
odoo/addons/auth_saml/controllers/__init__.py
odoo/addons/auth_saml/controllers/main.py
odoo/addons/auth_saml/data/auth_saml.xml
odoo/addons/auth_saml/data/ir_config_parameter.xml
odoo/addons/auth_saml/doc/Makefile
odoo/addons/auth_saml/doc/TODO.rst
odoo/addons/auth_saml/doc/autotodo
odoo/addons/auth_saml/doc/autotodo.py
odoo/addons/auth_saml/doc/conf.py
odoo/addons/auth_saml/doc/getting_started.rst
odoo/addons/auth_saml/doc/index.rst
odoo/addons/auth_saml/doc/models.gv
odoo/addons/auth_saml/doc/models.rst
odoo/addons/auth_saml/doc/requirements
odoo/addons/auth_saml/doc/tests.rst
odoo/addons/auth_saml/i18n/fr.po
odoo/addons/auth_saml/models/__init__.py
odoo/addons/auth_saml/models/auth_saml.py
odoo/addons/auth_saml/models/base_settings.py
odoo/addons/auth_saml/models/res_users.py
odoo/addons/auth_saml/models/saml_token.py
odoo/addons/auth_saml/scripts/2.0-cleanup.sql
odoo/addons/auth_saml/scripts/clear_passwords.sql
odoo/addons/auth_saml/security/ir.model.access.csv
odoo/addons/auth_saml/static/description/index.html
odoo/addons/auth_saml/tests/__init__.py
odoo/addons/auth_saml/tests/test_auth_saml.py
odoo/addons/auth_saml/tests/util/__init__.py
odoo/addons/auth_saml/tests/util/odoo_tests.py
odoo/addons/auth_saml/tests/util/singleton.py
odoo/addons/auth_saml/tests/util/uuidgen.py
odoo/addons/auth_saml/views/auth_saml.xml
odoo/addons/auth_saml/views/base_settings.xml
odoo/addons/auth_saml/views/res_users.xml
odoo11_addon_auth_saml-11.0.1.0.0.dist-info/DESCRIPTION.rst
odoo11_addon_auth_saml-11.0.1.0.0.dist-info/METADATA
odoo11_addon_auth_saml-11.0.1.0.0.dist-info/RECORD
odoo11_addon_auth_saml-11.0.1.0.0.dist-info/WHEEL
odoo11_addon_auth_saml-11.0.1.0.0.dist-info/metadata.json
odoo11_addon_auth_saml-11.0.1.0.0.dist-info/top_level.txt
